privateAB/__init__.py
privateAB/client.py
privateAB/data_generator.py
privateAB/discretizer.py
privateAB/server.py
privateAB/utils.py
privateAB/validate.py
privateAB-0.0.2.dist-info/METADATA
privateAB-0.0.2.dist-info/WHEEL
privateAB-0.0.2.dist-info/top_level.txt
privateAB-0.0.2.dist-info/RECORD
